design_sources/pc.v
module pc(
	input [31:0] D,
	input MODE,
	input ENABLE,
	input RES,
	input CLK,
	output reg [31:0] PC_OUT
	);
	
	always @(posedge CLK) begin
	   if (RES) begin
			PC_OUT = 32'h1A000000;
		end
		else begin
            if (ENABLE) begin
                if (MODE) begin
                    PC_OUT = D;
                end
                else begin
                    PC_OUT = PC_OUT + 4;
                end
            end
		end
	end
endmodule

simulation_sources/pc_tb.v
module pc_tb ();
	reg [31:0] D;
	reg MODE, ENABLE, RES, CLK;
	wire [31:0] PC_OUT;
	reg [31:0] soll;

	initial
		begin
			$dumpfile("pc_tb.vcd");
			$dumpvars(0,pc_tb);
		end

	pc dut(.D(D), .MODE(MODE), .ENABLE(ENABLE), .RES(RES), .CLK(CLK), .PC_OUT(PC_OUT));

	initial begin
		// initialwert
		D = 0; MODE = 0; ENABLE = 0; RES = 0; CLK = 0; soll = 32'h1A000000; #10;
		if (PC_OUT != soll)
		begin
			$display("Testmuster 1 Fehlgeschlagen: ist=%h soll=%h", PC_OUT, soll);
			$finish;
		end

		// hochzählen
		D = 0; MODE = 0; ENABLE = 1; RES = 0; CLK = 0; soll = 32'h1A000004; #10;
		CLK = 1; #10;
		if (PC_OUT != soll)
		begin
			$display("Testmuster 2 Fehlgeschlagen: ist=%h soll=%h", PC_OUT, soll);
			$finish;
		end

		// reset
		D = 0; MODE = 0; ENABLE = 1; RES = 1; CLK = 0; soll = 32'h1A000000; #10;
		CLK = 1; #10;
		if (PC_OUT != soll)
		begin
			$display("Testmuster 3 Fehlgeschlagen: ist=%h soll=%h", PC_OUT, soll);
			$finish;
		end

		// enable = 0
		D = 0; MODE = 0; ENABLE = 0; RES = 0; CLK = 0; soll = 32'h1A000000; #10;
		CLK = 1; #10;
		if (PC_OUT != soll)
		begin
			$display("Testmuster 1 Fehlgeschlagen: ist=%h soll=%h", PC_OUT, soll);
			$finish;
		end

		// mode = 1
		D = 0; MODE = 1; ENABLE = 1; RES = 0; CLK = 0; soll = 0; #10;
		CLK = 1; #10;
		if (PC_OUT != soll)
		begin
			$display("Testmuster 3 Fehlgeschlagen: ist=%h soll=%h", PC_OUT, soll);
			$finish;
		end
	end
endmodule

pc_tb.vcd
$date
	Fri Nov 29 13:46:57 2024
$end
$version
	Icarus Verilog
$end
$timescale
	1s
$end
$scope module pc_tb $end
$var wire 32 ! PC_OUT [31:0] $end
$var reg 1 " CLK $end
$var reg 32 # D [31:0] $end
$var reg 1 $ ENABLE $end
$var reg 1 % MODE $end
$var reg 1 & RES $end
$var reg 32 ' soll [31:0] $end
$scope module dut $end
$var wire 1 " CLK $end
$var wire 32 ( D [31:0] $end
$var wire 1 $ ENABLE $end
$var wire 1 % MODE $end
$var wire 1 & RES $end
$var reg 32 ) PC_OUT [31:0] $end
$upscope $end
$upscope $end
$enddefinitions $end
$comment Show the parameter values. $end
$dumpall
$end
#0
$dumpvars
b11010000000000000000000000000 )
b0 (
b11010000000000000000000000000 '
0&
0%
0$
b0 #
0"
b11010000000000000000000000000 !
$end
#10
b11010000000000000000000000100 '
1$
#20
b11010000000000000000000000100 !
b11010000000000000000000000100 )
1"
#30
b11010000000000000000000000000 '
0"
1&
#40
b11010000000000000000000000000 !
b11010000000000000000000000000 )
1"
#50
0"
0&
0$
#60
1"
#70
b0 '
0"
1$
1%
#80
b0 !
b0 )
1"
